nasbench_pytorch/__init__.py
nasbench_pytorch/trainer.py
nasbench_pytorch/datasets/__init__.py
nasbench_pytorch/datasets/cifar10.py
nasbench_pytorch/model/__init__.py
nasbench_pytorch/model/base_ops.py
nasbench_pytorch/model/graph_util.py
nasbench_pytorch/model/model.py
nasbench_pytorch/model/model_spec.py
nasbench_pytorch-1.3.1.dist-info/LICENSE.txt
nasbench_pytorch-1.3.1.dist-info/METADATA
nasbench_pytorch-1.3.1.dist-info/WHEEL
nasbench_pytorch-1.3.1.dist-info/top_level.txt
nasbench_pytorch-1.3.1.dist-info/RECORD
