Metadata-Version: 2.1
Name: nasbench-pytorch
Version: 1.3.1
Author: Romulus Hong, Gabriela Kadlecová
License: Apache License 2.0
License-File: LICENSE.txt
